seaflux/__init__.py
seaflux/_version.py
seaflux/area.py
seaflux/auxiliary_equations.py
seaflux/check_units.py
seaflux/fco2_pco2_conversion.py
seaflux/flux_calculations.py
seaflux/gas_transfer_velocity.py
seaflux/solubility.py
seaflux/vapour_pressure.py
seaflux/data/__init__.py
seaflux/data/aux_vars.py
seaflux/data/config.py
seaflux/data/download_zenodo_files.py
seaflux/data/jra55.py
seaflux/data/main.py
seaflux/data/pco2atm.py
seaflux/data/rdams_client.py
seaflux/data/spco2.py
seaflux/data/utils.py
seaflux/data/zenodo.yml
tests/__init__.py
tests/test_PyCO2SYS.py
tests/test_checks.py
tests/test_conversions.py
tests/test_fluxes.py
seaflux-2.1.1.dist-info/LICENSE.txt
seaflux-2.1.1.dist-info/METADATA
seaflux-2.1.1.dist-info/WHEEL
seaflux-2.1.1.dist-info/top_level.txt
seaflux-2.1.1.dist-info/RECORD
