Metadata-Version: 2.1
Name: seaflux
Version: 2.1.1
Summary: Calculation of air-sea fluxes
Home-page: https://github.com/lukegre/seaflux
Author: Luke Gregor
Author-email: luke.gregor@usys.ethz.ch
License: MIT
Platform: UNKNOWN
Classifier: Development Status :: 5 - Production/Stable
Classifier: Topic :: Scientific/Engineering
Classifier: Intended Audience :: Science/Research
Classifier: Operating System :: OS Independent
Classifier: Programming Language :: Python
Classifier: Programming Language :: Python :: 3
Classifier: Programming Language :: Python :: 3.7
Classifier: Programming Language :: Python :: 3.8
Classifier: License :: OSI Approved :: MIT License
Requires-Python: >=3.6
Requires-Dist: numpy
Requires-Dist: requests
Requires-Dist: fetch-data
